_thrustpy.cpython-312-x86_64-linux-gnu.so
thrustpy/_api.py
thrustpy/__init__.py
thrustpy-0.1.0a2.dist-info/top_level.txt
thrustpy-0.1.0a2.dist-info/WHEEL
thrustpy-0.1.0a2.dist-info/RECORD
thrustpy-0.1.0a2.dist-info/METADATA
thrustpy.libs/libgomp-a34b3233.so.1.0.0
